rfb_scpi_sniffer/__init__.py
rfb_scpi_sniffer/__version__.py
rfb_scpi_sniffer/context.py
rfb_scpi_sniffer/drv_scpi_cmd.py
rfb_scpi_sniffer/drv_scpi_iface.py
rfb_scpi_sniffer/drv_scpi_node.py
rfb_SCPI_sniffer-0.0.2.dist-info/LICENSE.txt
rfb_SCPI_sniffer-0.0.2.dist-info/METADATA
rfb_SCPI_sniffer-0.0.2.dist-info/WHEEL
rfb_SCPI_sniffer-0.0.2.dist-info/top_level.txt
rfb_SCPI_sniffer-0.0.2.dist-info/RECORD
