Metadata-Version: 2.1
Name: rfb-SCPI-sniffer
Version: 0.0.2
Summary: Broker used to send and receive SCPI commands through serial ports
Author-email: Raldea <r.aldea.csic+pypi@gmail.com>, Javier Sanz <javiersanzmoline@gmail.com>, Marius Crisan <mariuscrsn+pypi@gmail.com>, Pablo Pastor <pastorpflores+pypi@gmail.com>, Luis Roche <luis.roche@hotmail.com>
Maintainer-email: Javier Sanz <javiersanzmoline@gmail.com>, Raldea <r.aldea.csic+pypi@gmail.com>
License: GNU GENERAL PUBLIC LICENSE
Project-URL: Homepage, https://github.com/GIDEF-RFB/Battery-Cycler-Drivers
Project-URL: Bug Reports, https://github.com/GIDEF-RFB/Battery-Cycler-Drivers/issues
Project-URL: Bug Tracker, https://github.com/GIDEF-RFB/Battery-Cycler-Drivers/issues
Project-URL: Source, https://github.com/GIDEF-RFB/Battery-Cycler-Drivers/code/drv_scpi/src/rfb_scpi_sniffer
Project-URL: Funding, https://donate.pypi.org
Keywords: yaml,configuration,SCPI,sniffer,Embedded Systems,Serial
Classifier: Development Status :: 3 - Alpha
Classifier: Topic :: Software Development :: Embedded Systems
Classifier: Operating System :: OS Independent
Classifier: License :: OSI Approved :: GNU Affero General Public License v3
Classifier: Programming Language :: Python :: 3
Classifier: Programming Language :: Python :: 3.7
Classifier: Programming Language :: Python :: 3.8
Classifier: Programming Language :: Python :: 3.9
Classifier: Programming Language :: Python :: 3.10
Classifier: Programming Language :: Python :: 3 :: Only
Requires-Python: >=3.7
License-File: LICENSE.txt
Requires-Dist: pyserial >=3.5
Requires-Dist: rfb-logger-tool >=0.0.1
Requires-Dist: rfb-shared-tool >=0.0.1
